starlette_session/middleware/__init__.py
starlette_session/middleware/py.typed
starlette_session/middleware/authorizationbackends/__init__.py
starlette_session/middleware/authorizationbackends/authorizationheader.py
starlette_session/middleware/authorizationbackends/cookie.py
starlette_session/middleware/codecbackends/__init__.py
starlette_session/middleware/codecbackends/jwt.py
starlette_session/middleware/codecbackends/signer.py
starlette_session/middleware/storagebackends/__init__.py
starlette_session/middleware/storagebackends/cookie.py
starlette_session_middleware-0.1.6.dist-info/licenses/LICENSE
starlette_session_middleware-0.1.6.dist-info/METADATA
starlette_session_middleware-0.1.6.dist-info/WHEEL
starlette_session_middleware-0.1.6.dist-info/top_level.txt
starlette_session_middleware-0.1.6.dist-info/RECORD
