Metadata-Version: 2.4
Name: starlette-session-middleware
Version: 0.1.6
Summary: Enhanced and flexible ASGI session middleware for Starlette applications
Author-email: Anthony Lannutti <lannuttia@gmail.com>
License: MIT
Project-URL: Homepage, https://github.com/lannuttia/starlette-session-middleware
Project-URL: Repository, https://github.com/lannuttia/starlette-session-middleware
Project-URL: Issues, https://github.com/lannuttia/starlette-session-middleware/issues
Keywords: starlette,asgi,session,middleware,fastapi,jwt,cookie
Classifier: Development Status :: 4 - Beta
Classifier: Framework :: AsyncIO
Classifier: Intended Audience :: Developers
Classifier: License :: OSI Approved :: MIT License
Classifier: Operating System :: OS Independent
Classifier: Programming Language :: Python
Classifier: Programming Language :: Python :: 3
Classifier: Programming Language :: Python :: 3.9
Classifier: Programming Language :: Python :: 3.10
Classifier: Programming Language :: Python :: 3.11
Classifier: Programming Language :: Python :: 3.12
Classifier: Topic :: Internet :: WWW/HTTP :: Session
Classifier: Topic :: Software Development :: Libraries :: Python Modules
Classifier: Typing :: Typed
License-File: LICENSE
Requires-Dist: starlette~=0.35
Requires-Dist: typing_extensions>=3.10.0; python_version < "3.10"
Provides-Extra: itsdangerous
Requires-Dist: itsdangerous~=2.1; extra == "itsdangerous"
Provides-Extra: jwt
Requires-Dist: PyJWT~=2.8; extra == "jwt"
Dynamic: license-file
